{
  "consumption": [
    {
      "period": "month",
      "year": 2020,
      "month": 2,
      "beginDate": "2/1/2020",
      "endDate": "2/29/2020",
      "service": "storage",
      "unit": "TiB",
      "capacity": 150,
      "utilization": 132.8,
      "rate": 0.022,
      "cost": "$2,990.59",
      "currency": "USD"
    },
    {
      "period": "month",
      "year": 2020,
      "month": 3,
      "beginDate": "3/1/2020",
      "endDate": "3/31/2020",
      "service": "storage",
      "unit": "TiB",
      "capacity": 100,
      "utilization": 137.2,
      "rate": 0.022,
      "cost": "$3,090.49",
      "currency": "USD"
    },
    {
      "period": "month",
      "year": 2020,
      "month": 4,
      "beginDate": "4/1/2020",
      "endDate": "4/30/2020",
      "service": "storage",
      "unit": "TiB",
      "capacity": 100,
      "utilization": 130.6,
      "rate": 0.022,
      "cost": "$2,941.64",
      "currency": "USD"
    },
    {
      "period": "month",
      "year": 2020,
      "month": 5,
      "beginDate": "5/1/2020",
      "endDate": "5/31/2020",
      "service": "storage",
      "unit": "TiB",
      "capacity": 100,
      "utilization": 134.2,
      "rate": 0.022,
      "cost": "$3,022.18",
      "currency": "USD"
    },
    {
      "period": "month",
      "year": 2020,
      "month": 6,
      "beginDate": "6/1/2020",
      "endDate": "6/30/2020",
      "service": "storage",
      "unit": "TiB",
      "capacity": 100,
      "utilization": 138.6,
      "rate": 0.022,
      "cost": "$3,121.84",
      "currency": "USD"
    },
    {
      "period": "month",
      "year": 2020,
      "month": 7,
      "beginDate": "7/1/2020",
      "endDate": "7/31/2020",
      "service": "storage",
      "unit": "TiB",
      "capacity": 100,
      "utilization": 144.4,
      "rate": 0.022,
      "cost": "$3,252.96",
      "currency": "USD"
    },
    {
      "period": "month",
      "year": 2020,
      "month": 8,
      "beginDate": "8/1/2020",
      "endDate": "8/31/2020",
      "service": "storage",
      "unit": "TiB",
      "capacity": 100,
      "utilization": 148.5,
      "rate": 0.022,
      "cost": "$3,344.56",
      "currency": "USD"
    },
    {
      "period": "month",
      "year": 2020,
      "month": 9,
      "beginDate": "9/1/2020",
      "endDate": "9/30/2020",
      "service": "storage",
      "unit": "TiB",
      "capacity": 100,
      "utilization": 145.2,
      "rate": 0.022,
      "cost": "$3,271.14",
      "currency": "USD"
    },
    {
      "period": "month",
      "year": 2020,
      "month": 10,
      "beginDate": "10/1/2020",
      "endDate": "10/31/2020",
      "service": "storage",
      "unit": "TiB",
      "capacity": 100,
      "utilization": 151.2,
      "rate": 0.022,
      "cost": "$3,405.86",
      "currency": "USD"
    },
    {
      "period": "month",
      "year": 2020,
      "month": 11,
      "beginDate": "11/1/2020",
      "endDate": "11/30/2020",
      "service": "storage",
      "unit": "TiB",
      "capacity": 100,
      "utilization": 147,
      "rate": 0.022,
      "cost": "$3,312.45",
      "currency": "USD"
    },
    {
      "period": "month",
      "year": 2020,
      "month": 12,
      "beginDate": "12/1/2020",
      "endDate": "12/31/2020",
      "service": "storage",
      "unit": "TiB",
      "capacity": 100,
      "utilization": 153.2,
      "rate": 0.022,
      "cost": "$3,451.92",
      "currency": "USD"
    },
    {
      "period": "month",
      "year": 2021,
      "month": 1,
      "beginDate": "1/1/2021",
      "endDate": "1/31/2021",
      "service": "storage",
      "unit": "TiB",
      "capacity": 100,
      "utilization": 151.7,
      "rate": 0.022,
      "cost": "$3,416.57",
      "currency": "USD"
    },
    {
      "period": "month",
      "year": 2021,
      "month": 2,
      "beginDate": "2/1/2021",
      "endDate": "2/28/2021",
      "service": "storage",
      "unit": "TiB",
      "capacity": 100,
      "utilization": 153.8,
      "rate": 0.022,
      "cost": "$3,464.64",
      "currency": "USD"
    },
    {
      "period": "month",
      "year": 2021,
      "month": 3,
      "beginDate": "3/1/2021",
      "endDate": "3/31/2021",
      "service": "storage",
      "unit": "TiB",
      "capacity": 100,
      "utilization": 160.6,
      "rate": 0.022,
      "cost": "$3,618.31",
      "currency": "USD"
    },
    {
      "period": "month",
      "year": 2021,
      "month": 4,
      "beginDate": "4/1/2021",
      "endDate": "4/30/2021",
      "service": "storage",
      "unit": "TiB",
      "capacity": 100,
      "utilization": 164.4,
      "rate": 0.022,
      "cost": "$3,703.31",
      "currency": "USD"
    },
    {
      "period": "month",
      "year": 2021,
      "month": 5,
      "beginDate": "5/1/2021",
      "endDate": "5/31/2021",
      "service": "storage",
      "unit": "TiB",
      "capacity": 100,
      "utilization": 172.2,
      "rate": 0.022,
      "cost": "$3,878.82",
      "currency": "USD"
    },
    {
      "period": "month",
      "year": 2021,
      "month": 6,
      "beginDate": "6/1/2021",
      "endDate": "6/30/2021",
      "service": "storage",
      "unit": "TiB",
      "capacity": 100,
      "utilization": 168.4,
      "rate": 0.022,
      "cost": "$3,794.13",
      "currency": "USD"
    },
    {
      "period": "month",
      "year": 2021,
      "month": 7,
      "beginDate": "7/1/2021",
      "endDate": "7/31/2021",
      "service": "storage",
      "unit": "TiB",
      "capacity": 100,
      "utilization": 163.1,
      "rate": 0.022,
      "cost": "$3,675.18",
      "currency": "USD"
    },
    {
      "period": "month",
      "year": 2021,
      "month": 8,
      "beginDate": "8/1/2021",
      "endDate": "8/31/2021",
      "service": "storage",
      "unit": "TiB",
      "capacity": 100,
      "utilization": 169.8,
      "rate": 0.022,
      "cost": "$3,825.14",
      "currency": "USD"
    },
    {
      "period": "month",
      "year": 2021,
      "month": 9,
      "beginDate": "9/1/2021",
      "endDate": "9/30/2021",
      "service": "storage",
      "unit": "TiB",
      "capacity": 100,
      "utilization": 170.1,
      "rate": 0.022,
      "cost": "$3,832.16",
      "currency": "USD"
    },
    {
      "period": "month",
      "year": 2021,
      "month": 10,
      "beginDate": "10/1/2021",
      "endDate": "10/31/2021",
      "service": "storage",
      "unit": "TiB",
      "capacity": 100,
      "utilization": 177.9,
      "rate": 0.022,
      "cost": "$4,007.61",
      "currency": "USD"
    },
    {
      "period": "month",
      "year": 2021,
      "month": 11,
      "beginDate": "11/1/2021",
      "endDate": "11/30/2021",
      "service": "storage",
      "unit": "TiB",
      "capacity": 100,
      "utilization": 176.5,
      "rate": 0.022,
      "cost": "$3,976.02",
      "currency": "USD"
    },
    {
      "period": "month",
      "year": 2021,
      "month": 12,
      "beginDate": "12/1/2021",
      "endDate": "12/31/2021",
      "service": "storage",
      "unit": "TiB",
      "capacity": 100,
      "utilization": 167.9,
      "rate": 0.022,
      "cost": "$3,782.19",
      "currency": "USD"
    },
    {
      "period": "month",
      "year": 2022,
      "month": 1,
      "beginDate": "1/1/2022",
      "endDate": "1/31/2022",
      "service": "storage",
      "unit": "TiB",
      "capacity": 100,
      "utilization": 173.2,
      "rate": 0.022,
      "cost": "$3,900.75",
      "currency": "USD"
    },
    {
      "period": "month",
      "year": 2020,
      "month": 2,
      "beginDate": "2/1/2020",
      "endDate": "2/29/2020",
      "service": "compute",
      "unit": "CPU",
      "capacity": 650,
      "utilization": 489,
      "rate": 0.022,
      "cost": "$11,016.19",
      "currency": "USD"
    },
    {
      "period": "month",
      "year": 2020,
      "month": 3,
      "beginDate": "3/1/2020",
      "endDate": "3/31/2020",
      "service": "compute",
      "unit": "CPU",
      "capacity": 650,
      "utilization": 480.3,
      "rate": 0.022,
      "cost": "$10,819.66",
      "currency": "USD"
    },
    {
      "period": "month",
      "year": 2020,
      "month": 4,
      "beginDate": "4/1/2020",
      "endDate": "4/30/2020",
      "service": "compute",
      "unit": "CPU",
      "capacity": 650,
      "utilization": 458.7,
      "rate": 0.022,
      "cost": "$10,333.11",
      "currency": "USD"
    },
    {
      "period": "month",
      "year": 2020,
      "month": 5,
      "beginDate": "5/1/2020",
      "endDate": "5/31/2020",
      "service": "compute",
      "unit": "CPU",
      "capacity": 650,
      "utilization": 435.9,
      "rate": 0.022,
      "cost": "$9,819.02",
      "currency": "USD"
    },
    {
      "period": "month",
      "year": 2020,
      "month": 6,
      "beginDate": "6/1/2020",
      "endDate": "6/30/2020",
      "service": "compute",
      "unit": "CPU",
      "capacity": 650,
      "utilization": 454.4,
      "rate": 0.022,
      "cost": "$10,237.59",
      "currency": "USD"
    },
    {
      "period": "month",
      "year": 2020,
      "month": 7,
      "beginDate": "7/1/2020",
      "endDate": "7/31/2020",
      "service": "compute",
      "unit": "CPU",
      "capacity": 650,
      "utilization": 454.1,
      "rate": 0.022,
      "cost": "$10,230.34",
      "currency": "USD"
    },
    {
      "period": "month",
      "year": 2020,
      "month": 8,
      "beginDate": "8/1/2020",
      "endDate": "8/31/2020",
      "service": "compute",
      "unit": "CPU",
      "capacity": 650,
      "utilization": 433.9,
      "rate": 0.022,
      "cost": "$9,773.93",
      "currency": "USD"
    },
    {
      "period": "month",
      "year": 2020,
      "month": 9,
      "beginDate": "9/1/2020",
      "endDate": "9/30/2020",
      "service": "compute",
      "unit": "CPU",
      "capacity": 650,
      "utilization": 445.7,
      "rate": 0.022,
      "cost": "$10,040.19",
      "currency": "USD"
    },
    {
      "period": "month",
      "year": 2020,
      "month": 10,
      "beginDate": "10/1/2020",
      "endDate": "10/31/2020",
      "service": "compute",
      "unit": "CPU",
      "capacity": 650,
      "utilization": 430.2,
      "rate": 0.022,
      "cost": "$9,691.72",
      "currency": "USD"
    },
    {
      "period": "month",
      "year": 2020,
      "month": 11,
      "beginDate": "11/1/2020",
      "endDate": "11/30/2020",
      "service": "compute",
      "unit": "CPU",
      "capacity": 650,
      "utilization": 428.7,
      "rate": 0.022,
      "cost": "$9,657.37",
      "currency": "USD"
    },
    {
      "period": "month",
      "year": 2020,
      "month": 12,
      "beginDate": "12/1/2020",
      "endDate": "12/31/2020",
      "service": "compute",
      "unit": "CPU",
      "capacity": 650,
      "utilization": 418.7,
      "rate": 0.022,
      "cost": "$9,431.88",
      "currency": "USD"
    },
    {
      "period": "month",
      "year": 2021,
      "month": 1,
      "beginDate": "1/1/2021",
      "endDate": "1/31/2021",
      "service": "compute",
      "unit": "CPU",
      "capacity": 650,
      "utilization": 422.3,
      "rate": 0.022,
      "cost": "$9,513.97",
      "currency": "USD"
    },
    {
      "period": "month",
      "year": 2021,
      "month": 2,
      "beginDate": "2/1/2021",
      "endDate": "2/28/2021",
      "service": "compute",
      "unit": "CPU",
      "capacity": 650,
      "utilization": 424.7,
      "rate": 0.022,
      "cost": "$9,566.65",
      "currency": "USD"
    },
    {
      "period": "month",
      "year": 2021,
      "month": 3,
      "beginDate": "3/1/2021",
      "endDate": "3/31/2021",
      "service": "compute",
      "unit": "CPU",
      "capacity": 650,
      "utilization": 424.3,
      "rate": 0.022,
      "cost": "$9,559.19",
      "currency": "USD"
    },
    {
      "period": "month",
      "year": 2021,
      "month": 4,
      "beginDate": "4/1/2021",
      "endDate": "4/30/2021",
      "service": "compute",
      "unit": "CPU",
      "capacity": 650,
      "utilization": 432.6,
      "rate": 0.022,
      "cost": "$9,745.10",
      "currency": "USD"
    },
    {
      "period": "month",
      "year": 2021,
      "month": 5,
      "beginDate": "5/1/2021",
      "endDate": "5/31/2021",
      "service": "compute",
      "unit": "CPU",
      "capacity": 650,
      "utilization": 425.5,
      "rate": 0.022,
      "cost": "$9,586.55",
      "currency": "USD"
    },
    {
      "period": "month",
      "year": 2021,
      "month": 6,
      "beginDate": "6/1/2021",
      "endDate": "6/30/2021",
      "service": "compute",
      "unit": "CPU",
      "capacity": 650,
      "utilization": 426.7,
      "rate": 0.022,
      "cost": "$9,612.44",
      "currency": "USD"
    },
    {
      "period": "month",
      "year": 2021,
      "month": 7,
      "beginDate": "7/1/2021",
      "endDate": "7/31/2021",
      "service": "compute",
      "unit": "CPU",
      "capacity": 650,
      "utilization": 414.4,
      "rate": 0.022,
      "cost": "$9,334.93",
      "currency": "USD"
    },
    {
      "period": "month",
      "year": 2021,
      "month": 8,
      "beginDate": "8/1/2021",
      "endDate": "8/31/2021",
      "service": "compute",
      "unit": "CPU",
      "capacity": 650,
      "utilization": 404.3,
      "rate": 0.022,
      "cost": "$9,107.29",
      "currency": "USD"
    },
    {
      "period": "month",
      "year": 2021,
      "month": 9,
      "beginDate": "9/1/2021",
      "endDate": "9/30/2021",
      "service": "compute",
      "unit": "CPU",
      "capacity": 500,
      "utilization": 389.2,
      "rate": 0.022,
      "cost": "$8,768.56",
      "currency": "USD"
    },
    {
      "period": "month",
      "year": 2021,
      "month": 10,
      "beginDate": "10/1/2021",
      "endDate": "10/31/2021",
      "service": "compute",
      "unit": "CPU",
      "capacity": 500,
      "utilization": 379.8,
      "rate": 0.022,
      "cost": "$8,556.58",
      "currency": "USD"
    },
    {
      "period": "month",
      "year": 2021,
      "month": 11,
      "beginDate": "11/1/2021",
      "endDate": "11/30/2021",
      "service": "compute",
      "unit": "CPU",
      "capacity": 500,
      "utilization": 374.2,
      "rate": 0.022,
      "cost": "$8,429.93",
      "currency": "USD"
    },
    {
      "period": "month",
      "year": 2021,
      "month": 12,
      "beginDate": "12/1/2021",
      "endDate": "12/31/2021",
      "service": "compute",
      "unit": "CPU",
      "capacity": 500,
      "utilization": 373,
      "rate": 0.022,
      "cost": "$8,403.34",
      "currency": "USD"
    },
    {
      "period": "month",
      "year": 2022,
      "month": 1,
      "beginDate": "1/1/2022",
      "endDate": "1/31/2022",
      "service": "compute",
      "unit": "CPU",
      "capacity": 500,
      "utilization": 379,
      "rate": 0.022,
      "cost": "$8,538.74",
      "currency": "USD"
    },
    {
      "period": "month",
      "year": 2020,
      "month": 2,
      "beginDate": "2/1/2020",
      "endDate": "2/29/2020",
      "service": "database",
      "unit": "DTU",
      "capacity": 200,
      "utilization": 150,
      "rate": 0.032,
      "cost": "$4,915.20",
      "currency": "USD"
    },
    {
      "period": "month",
      "year": 2020,
      "month": 3,
      "beginDate": "3/1/2020",
      "endDate": "3/31/2020",
      "service": "database",
      "unit": "DTU",
      "capacity": 200,
      "utilization": 150,
      "rate": 0.032,
      "cost": "$4,915.20",
      "currency": "USD"
    },
    {
      "period": "month",
      "year": 2020,
      "month": 4,
      "beginDate": "4/1/2020",
      "endDate": "4/30/2020",
      "service": "database",
      "unit": "DTU",
      "capacity": 200,
      "utilization": 150,
      "rate": 0.032,
      "cost": "$4,915.20",
      "currency": "USD"
    },
    {
      "period": "month",
      "year": 2020,
      "month": 5,
      "beginDate": "5/1/2020",
      "endDate": "5/31/2020",
      "service": "database",
      "unit": "DTU",
      "capacity": 200,
      "utilization": 150,
      "rate": 0.032,
      "cost": "$4,915.20",
      "currency": "USD"
    },
    {
      "period": "month",
      "year": 2020,
      "month": 6,
      "beginDate": "6/1/2020",
      "endDate": "6/30/2020",
      "service": "database",
      "unit": "DTU",
      "capacity": 200,
      "utilization": 150,
      "rate": 0.032,
      "cost": "$4,915.20",
      "currency": "USD"
    },
    {
      "period": "month",
      "year": 2020,
      "month": 7,
      "beginDate": "7/1/2020",
      "endDate": "7/31/2020",
      "service": "database",
      "unit": "DTU",
      "capacity": 200,
      "utilization": 150,
      "rate": 0.032,
      "cost": "$4,915.20",
      "currency": "USD"
    },
    {
      "period": "month",
      "year": 2020,
      "month": 8,
      "beginDate": "8/1/2020",
      "endDate": "8/31/2020",
      "service": "database",
      "unit": "DTU",
      "capacity": 200,
      "utilization": 150,
      "rate": 0.032,
      "cost": "$4,915.20",
      "currency": "USD"
    },
    {
      "period": "month",
      "year": 2020,
      "month": 9,
      "beginDate": "9/1/2020",
      "endDate": "9/30/2020",
      "service": "database",
      "unit": "DTU",
      "capacity": 200,
      "utilization": 150,
      "rate": 0.032,
      "cost": "$4,915.20",
      "currency": "USD"
    },
    {
      "period": "month",
      "year": 2020,
      "month": 10,
      "beginDate": "10/1/2020",
      "endDate": "10/31/2020",
      "service": "database",
      "unit": "DTU",
      "capacity": 200,
      "utilization": 150,
      "rate": 0.032,
      "cost": "$4,915.20",
      "currency": "USD"
    },
    {
      "period": "month",
      "year": 2020,
      "month": 11,
      "beginDate": "11/1/2020",
      "endDate": "11/30/2020",
      "service": "database",
      "unit": "DTU",
      "capacity": 200,
      "utilization": 150,
      "rate": 0.032,
      "cost": "$4,915.20",
      "currency": "USD"
    },
    {
      "period": "month",
      "year": 2020,
      "month": 12,
      "beginDate": "12/1/2020",
      "endDate": "12/31/2020",
      "service": "database",
      "unit": "DTU",
      "capacity": 200,
      "utilization": 150,
      "rate": 0.032,
      "cost": "$4,915.20",
      "currency": "USD"
    },
    {
      "period": "month",
      "year": 2021,
      "month": 1,
      "beginDate": "1/1/2021",
      "endDate": "1/31/2021",
      "service": "database",
      "unit": "DTU",
      "capacity": 200,
      "utilization": 150,
      "rate": 0.032,
      "cost": "$4,915.20",
      "currency": "USD"
    },
    {
      "period": "month",
      "year": 2021,
      "month": 2,
      "beginDate": "2/1/2021",
      "endDate": "2/28/2021",
      "service": "database",
      "unit": "DTU",
      "capacity": 200,
      "utilization": 150,
      "rate": 0.032,
      "cost": "$4,915.20",
      "currency": "USD"
    },
    {
      "period": "month",
      "year": 2021,
      "month": 3,
      "beginDate": "3/1/2021",
      "endDate": "3/31/2021",
      "service": "database",
      "unit": "DTU",
      "capacity": 200,
      "utilization": 150,
      "rate": 0.032,
      "cost": "$4,915.20",
      "currency": "USD"
    },
    {
      "period": "month",
      "year": 2021,
      "month": 4,
      "beginDate": "4/1/2021",
      "endDate": "4/30/2021",
      "service": "database",
      "unit": "DTU",
      "capacity": 200,
      "utilization": 150,
      "rate": 0.032,
      "cost": "$4,915.20",
      "currency": "USD"
    },
    {
      "period": "month",
      "year": 2021,
      "month": 5,
      "beginDate": "5/1/2021",
      "endDate": "5/31/2021",
      "service": "database",
      "unit": "DTU",
      "capacity": 200,
      "utilization": 150,
      "rate": 0.032,
      "cost": "$4,915.20",
      "currency": "USD"
    },
    {
      "period": "month",
      "year": 2021,
      "month": 6,
      "beginDate": "6/1/2021",
      "endDate": "6/30/2021",
      "service": "database",
      "unit": "DTU",
      "capacity": 200,
      "utilization": 150,
      "rate": 0.032,
      "cost": "$4,915.20",
      "currency": "USD"
    },
    {
      "period": "month",
      "year": 2021,
      "month": 7,
      "beginDate": "7/1/2021",
      "endDate": "7/31/2021",
      "service": "database",
      "unit": "DTU",
      "capacity": 200,
      "utilization": 150,
      "rate": 0.032,
      "cost": "$4,915.20",
      "currency": "USD"
    },
    {
      "period": "month",
      "year": 2021,
      "month": 8,
      "beginDate": "8/1/2021",
      "endDate": "8/31/2021",
      "service": "database",
      "unit": "DTU",
      "capacity": 200,
      "utilization": 150,
      "rate": 0.032,
      "cost": "$4,915.20",
      "currency": "USD"
    },
    {
      "period": "month",
      "year": 2021,
      "month": 9,
      "beginDate": "9/1/2021",
      "endDate": "9/30/2021",
      "service": "database",
      "unit": "DTU",
      "capacity": 200,
      "utilization": 150,
      "rate": 0.032,
      "cost": "$4,915.20",
      "currency": "USD"
    },
    {
      "period": "month",
      "year": 2021,
      "month": 10,
      "beginDate": "10/1/2021",
      "endDate": "10/31/2021",
      "service": "database",
      "unit": "DTU",
      "capacity": 200,
      "utilization": 150,
      "rate": 0.032,
      "cost": "$4,915.20",
      "currency": "USD"
    },
    {
      "period": "month",
      "year": 2021,
      "month": 11,
      "beginDate": "11/1/2021",
      "endDate": "11/30/2021",
      "service": "database",
      "unit": "DTU",
      "capacity": 200,
      "utilization": 150,
      "rate": 0.032,
      "cost": "$4,915.20",
      "currency": "USD"
    },
    {
      "period": "month",
      "year": 2021,
      "month": 12,
      "beginDate": "12/1/2021",
      "endDate": "12/31/2021",
      "service": "database",
      "unit": "DTU",
      "capacity": 200,
      "utilization": 150,
      "rate": 0.032,
      "cost": "$4,915.20",
      "currency": "USD"
    },
    {
      "period": "month",
      "year": 2022,
      "month": 1,
      "beginDate": "1/1/2022",
      "endDate": "1/31/2022",
      "service": "database",
      "unit": "DTU",
      "capacity": 200,
      "utilization": 150,
      "rate": 0.032,
      "cost": "$4,915.20",
      "currency": "USD"
    },
    {
      "period": "month",
      "year": 2020,
      "month": 2,
      "beginDate": "2/1/2020",
      "endDate": "2/29/2020",
      "service": "operations",
      "unit": "OPS",
      "capacity": 100,
      "utilization": 82,
      "rate": 0.012,
      "cost": "$1,007.62",
      "currency": "USD"
    },
    {
      "period": "month",
      "year": 2020,
      "month": 3,
      "beginDate": "3/1/2020",
      "endDate": "3/31/2020",
      "service": "operations",
      "unit": "OPS",
      "capacity": 100,
      "utilization": 78.4,
      "rate": 0.012,
      "cost": "$963.70",
      "currency": "USD"
    },
    {
      "period": "month",
      "year": 2020,
      "month": 4,
      "beginDate": "4/1/2020",
      "endDate": "4/30/2020",
      "service": "operations",
      "unit": "OPS",
      "capacity": 100,
      "utilization": 82,
      "rate": 0.012,
      "cost": "$1,008.00",
      "currency": "USD"
    },
    {
      "period": "month",
      "year": 2020,
      "month": 5,
      "beginDate": "5/1/2020",
      "endDate": "5/31/2020",
      "service": "operations",
      "unit": "OPS",
      "capacity": 100,
      "utilization": 85.3,
      "rate": 0.012,
      "cost": "$1,047.86",
      "currency": "USD"
    },
    {
      "period": "month",
      "year": 2020,
      "month": 6,
      "beginDate": "6/1/2020",
      "endDate": "6/30/2020",
      "service": "operations",
      "unit": "OPS",
      "capacity": 100,
      "utilization": 83.1,
      "rate": 0.012,
      "cost": "$1,020.80",
      "currency": "USD"
    },
    {
      "period": "month",
      "year": 2020,
      "month": 7,
      "beginDate": "7/1/2020",
      "endDate": "7/31/2020",
      "service": "operations",
      "unit": "OPS",
      "capacity": 100,
      "utilization": 81.3,
      "rate": 0.012,
      "cost": "$998.69",
      "currency": "USD"
    },
    {
      "period": "month",
      "year": 2020,
      "month": 8,
      "beginDate": "8/1/2020",
      "endDate": "8/31/2020",
      "service": "operations",
      "unit": "OPS",
      "capacity": 100,
      "utilization": 85.1,
      "rate": 0.012,
      "cost": "$1,045.80",
      "currency": "USD"
    },
    {
      "period": "month",
      "year": 2020,
      "month": 9,
      "beginDate": "9/1/2020",
      "endDate": "9/30/2020",
      "service": "operations",
      "unit": "OPS",
      "capacity": 100,
      "utilization": 86.2,
      "rate": 0.012,
      "cost": "$1,058.84",
      "currency": "USD"
    },
    {
      "period": "month",
      "year": 2020,
      "month": 10,
      "beginDate": "10/1/2020",
      "endDate": "10/31/2020",
      "service": "operations",
      "unit": "OPS",
      "capacity": 100,
      "utilization": 81.9,
      "rate": 0.012,
      "cost": "$1,006.69",
      "currency": "USD"
    },
    {
      "period": "month",
      "year": 2020,
      "month": 11,
      "beginDate": "11/1/2020",
      "endDate": "11/30/2020",
      "service": "operations",
      "unit": "OPS",
      "capacity": 100,
      "utilization": 84.9,
      "rate": 0.012,
      "cost": "$1,043.02",
      "currency": "USD"
    },
    {
      "period": "month",
      "year": 2020,
      "month": 12,
      "beginDate": "12/1/2020",
      "endDate": "12/31/2020",
      "service": "operations",
      "unit": "OPS",
      "capacity": 100,
      "utilization": 87.8,
      "rate": 0.012,
      "cost": "$1,079.24",
      "currency": "USD"
    },
    {
      "period": "month",
      "year": 2021,
      "month": 1,
      "beginDate": "1/1/2021",
      "endDate": "1/31/2021",
      "service": "operations",
      "unit": "OPS",
      "capacity": 100,
      "utilization": 89.1,
      "rate": 0.012,
      "cost": "$1,094.93",
      "currency": "USD"
    },
    {
      "period": "month",
      "year": 2021,
      "month": 2,
      "beginDate": "2/1/2021",
      "endDate": "2/28/2021",
      "service": "operations",
      "unit": "OPS",
      "capacity": 100,
      "utilization": 86,
      "rate": 0.012,
      "cost": "$1,056.98",
      "currency": "USD"
    },
    {
      "period": "month",
      "year": 2021,
      "month": 3,
      "beginDate": "3/1/2021",
      "endDate": "3/31/2021",
      "service": "operations",
      "unit": "OPS",
      "capacity": 100,
      "utilization": 88.5,
      "rate": 0.012,
      "cost": "$1,087.22",
      "currency": "USD"
    },
    {
      "period": "month",
      "year": 2021,
      "month": 4,
      "beginDate": "4/1/2021",
      "endDate": "4/30/2021",
      "service": "operations",
      "unit": "OPS",
      "capacity": 100,
      "utilization": 90.3,
      "rate": 0.012,
      "cost": "$1,109.78",
      "currency": "USD"
    },
    {
      "period": "month",
      "year": 2021,
      "month": 5,
      "beginDate": "5/1/2021",
      "endDate": "5/31/2021",
      "service": "operations",
      "unit": "OPS",
      "capacity": 100,
      "utilization": 92.7,
      "rate": 0.012,
      "cost": "$1,138.80",
      "currency": "USD"
    },
    {
      "period": "month",
      "year": 2021,
      "month": 6,
      "beginDate": "6/1/2021",
      "endDate": "6/30/2021",
      "service": "operations",
      "unit": "OPS",
      "capacity": 100,
      "utilization": 92.8,
      "rate": 0.012,
      "cost": "$1,140.46",
      "currency": "USD"
    },
    {
      "period": "month",
      "year": 2021,
      "month": 7,
      "beginDate": "7/1/2021",
      "endDate": "7/31/2021",
      "service": "operations",
      "unit": "OPS",
      "capacity": 100,
      "utilization": 90.7,
      "rate": 0.012,
      "cost": "$1,114.80",
      "currency": "USD"
    },
    {
      "period": "month",
      "year": 2021,
      "month": 8,
      "beginDate": "8/1/2021",
      "endDate": "8/31/2021",
      "service": "operations",
      "unit": "OPS",
      "capacity": 100,
      "utilization": 87,
      "rate": 0.012,
      "cost": "$1,069.66",
      "currency": "USD"
    },
    {
      "period": "month",
      "year": 2021,
      "month": 9,
      "beginDate": "9/1/2021",
      "endDate": "9/30/2021",
      "service": "operations",
      "unit": "OPS",
      "capacity": 100,
      "utilization": 87.9,
      "rate": 0.012,
      "cost": "$1,080.05",
      "currency": "USD"
    },
    {
      "period": "month",
      "year": 2021,
      "month": 10,
      "beginDate": "10/1/2021",
      "endDate": "10/31/2021",
      "service": "operations",
      "unit": "OPS",
      "capacity": 100,
      "utilization": 91,
      "rate": 0.012,
      "cost": "$1,117.83",
      "currency": "USD"
    },
    {
      "period": "month",
      "year": 2021,
      "month": 11,
      "beginDate": "11/1/2021",
      "endDate": "11/30/2021",
      "service": "operations",
      "unit": "OPS",
      "capacity": 100,
      "utilization": 95.1,
      "rate": 0.012,
      "cost": "$1,168.77",
      "currency": "USD"
    },
    {
      "period": "month",
      "year": 2021,
      "month": 12,
      "beginDate": "12/1/2021",
      "endDate": "12/31/2021",
      "service": "operations",
      "unit": "OPS",
      "capacity": 100,
      "utilization": 90.7,
      "rate": 0.012,
      "cost": "$1,115.13",
      "currency": "USD"
    },
    {
      "period": "month",
      "year": 2022,
      "month": 1,
      "beginDate": "1/1/2022",
      "endDate": "1/31/2022",
      "service": "operations",
      "unit": "OPS",
      "capacity": 100,
      "utilization": 89.1,
      "rate": 0.012,
      "cost": "$1,095.17",
      "currency": "USD"
    },
    {
      "period": "month",
      "year": 2020,
      "month": 2,
      "beginDate": "2/1/2020",
      "endDate": "2/29/2020",
      "service": "uncategorized",
      "unit": "widgets",
      "capacity": 100,
      "utilization": 55,
      "rate": 0.041,
      "cost": "$2,309.12",
      "currency": "USD"
    },
    {
      "period": "month",
      "year": 2020,
      "month": 3,
      "beginDate": "3/1/2020",
      "endDate": "3/31/2020",
      "service": "uncategorized",
      "unit": "widgets",
      "capacity": 100,
      "utilization": 55.4,
      "rate": 0.041,
      "cost": "$2,326.11",
      "currency": "USD"
    },
    {
      "period": "month",
      "year": 2020,
      "month": 4,
      "beginDate": "4/1/2020",
      "endDate": "4/30/2020",
      "service": "uncategorized",
      "unit": "widgets",
      "capacity": 100,
      "utilization": 54.5,
      "rate": 0.041,
      "cost": "$2,290.00",
      "currency": "USD"
    },
    {
      "period": "month",
      "year": 2020,
      "month": 5,
      "beginDate": "5/1/2020",
      "endDate": "5/31/2020",
      "service": "uncategorized",
      "unit": "widgets",
      "capacity": 100,
      "utilization": 55,
      "rate": 0.041,
      "cost": "$2,310.73",
      "currency": "USD"
    },
    {
      "period": "month",
      "year": 2020,
      "month": 6,
      "beginDate": "6/1/2020",
      "endDate": "6/30/2020",
      "service": "uncategorized",
      "unit": "widgets",
      "capacity": 100,
      "utilization": 57.5,
      "rate": 0.041,
      "cost": "$2,415.38",
      "currency": "USD"
    },
    {
      "period": "month",
      "year": 2020,
      "month": 7,
      "beginDate": "7/1/2020",
      "endDate": "7/31/2020",
      "service": "uncategorized",
      "unit": "widgets",
      "capacity": 100,
      "utilization": 57.4,
      "rate": 0.041,
      "cost": "$2,409.85",
      "currency": "USD"
    },
    {
      "period": "month",
      "year": 2020,
      "month": 8,
      "beginDate": "8/1/2020",
      "endDate": "8/31/2020",
      "service": "uncategorized",
      "unit": "widgets",
      "capacity": 100,
      "utilization": 57.9,
      "rate": 0.041,
      "cost": "$2,431.59",
      "currency": "USD"
    },
    {
      "period": "month",
      "year": 2020,
      "month": 9,
      "beginDate": "9/1/2020",
      "endDate": "9/30/2020",
      "service": "uncategorized",
      "unit": "widgets",
      "capacity": 100,
      "utilization": 56.9,
      "rate": 0.041,
      "cost": "$2,388.89",
      "currency": "USD"
    },
    {
      "period": "month",
      "year": 2020,
      "month": 10,
      "beginDate": "10/1/2020",
      "endDate": "10/31/2020",
      "service": "uncategorized",
      "unit": "widgets",
      "capacity": 100,
      "utilization": 56.9,
      "rate": 0.041,
      "cost": "$2,388.69",
      "currency": "USD"
    },
    {
      "period": "month",
      "year": 2020,
      "month": 11,
      "beginDate": "11/1/2020",
      "endDate": "11/30/2020",
      "service": "uncategorized",
      "unit": "widgets",
      "capacity": 100,
      "utilization": 55.2,
      "rate": 0.041,
      "cost": "$2,315.85",
      "currency": "USD"
    },
    {
      "period": "month",
      "year": 2020,
      "month": 12,
      "beginDate": "12/1/2020",
      "endDate": "12/31/2020",
      "service": "uncategorized",
      "unit": "widgets",
      "capacity": 100,
      "utilization": 56.8,
      "rate": 0.041,
      "cost": "$2,383.08",
      "currency": "USD"
    },
    {
      "period": "month",
      "year": 2021,
      "month": 1,
      "beginDate": "1/1/2021",
      "endDate": "1/31/2021",
      "service": "uncategorized",
      "unit": "widgets",
      "capacity": 100,
      "utilization": 57.9,
      "rate": 0.041,
      "cost": "$2,430.48",
      "currency": "USD"
    },
    {
      "period": "month",
      "year": 2021,
      "month": 2,
      "beginDate": "2/1/2021",
      "endDate": "2/28/2021",
      "service": "uncategorized",
      "unit": "widgets",
      "capacity": 100,
      "utilization": 59.1,
      "rate": 0.041,
      "cost": "$2,481.96",
      "currency": "USD"
    },
    {
      "period": "month",
      "year": 2021,
      "month": 3,
      "beginDate": "3/1/2021",
      "endDate": "3/31/2021",
      "service": "uncategorized",
      "unit": "widgets",
      "capacity": 100,
      "utilization": 60.8,
      "rate": 0.041,
      "cost": "$2,552.05",
      "currency": "USD"
    },
    {
      "period": "month",
      "year": 2021,
      "month": 4,
      "beginDate": "4/1/2021",
      "endDate": "4/30/2021",
      "service": "uncategorized",
      "unit": "widgets",
      "capacity": 100,
      "utilization": 59,
      "rate": 0.041,
      "cost": "$2,476.13",
      "currency": "USD"
    },
    {
      "period": "month",
      "year": 2021,
      "month": 5,
      "beginDate": "5/1/2021",
      "endDate": "5/31/2021",
      "service": "uncategorized",
      "unit": "widgets",
      "capacity": 100,
      "utilization": 57.3,
      "rate": 0.041,
      "cost": "$2,405.93",
      "currency": "USD"
    },
    {
      "period": "month",
      "year": 2021,
      "month": 6,
      "beginDate": "6/1/2021",
      "endDate": "6/30/2021",
      "service": "uncategorized",
      "unit": "widgets",
      "capacity": 100,
      "utilization": 60,
      "rate": 0.041,
      "cost": "$2,517.13",
      "currency": "USD"
    },
    {
      "period": "month",
      "year": 2021,
      "month": 7,
      "beginDate": "7/1/2021",
      "endDate": "7/31/2021",
      "service": "uncategorized",
      "unit": "widgets",
      "capacity": 100,
      "utilization": 61.7,
      "rate": 0.041,
      "cost": "$2,590.10",
      "currency": "USD"
    },
    {
      "period": "month",
      "year": 2021,
      "month": 8,
      "beginDate": "8/1/2021",
      "endDate": "8/31/2021",
      "service": "uncategorized",
      "unit": "widgets",
      "capacity": 100,
      "utilization": 60.5,
      "rate": 0.041,
      "cost": "$2,539.72",
      "currency": "USD"
    },
    {
      "period": "month",
      "year": 2021,
      "month": 9,
      "beginDate": "9/1/2021",
      "endDate": "9/30/2021",
      "service": "uncategorized",
      "unit": "widgets",
      "capacity": 100,
      "utilization": 60.7,
      "rate": 0.041,
      "cost": "$2,550.07",
      "currency": "USD"
    },
    {
      "period": "month",
      "year": 2021,
      "month": 10,
      "beginDate": "10/1/2021",
      "endDate": "10/31/2021",
      "service": "uncategorized",
      "unit": "widgets",
      "capacity": 100,
      "utilization": 61.2,
      "rate": 0.041,
      "cost": "$2,570.40",
      "currency": "USD"
    },
    {
      "period": "month",
      "year": 2021,
      "month": 11,
      "beginDate": "11/1/2021",
      "endDate": "11/30/2021",
      "service": "uncategorized",
      "unit": "widgets",
      "capacity": 100,
      "utilization": 62.2,
      "rate": 0.041,
      "cost": "$2,609.73",
      "currency": "USD"
    },
    {
      "period": "month",
      "year": 2021,
      "month": 12,
      "beginDate": "12/1/2021",
      "endDate": "12/31/2021",
      "service": "uncategorized",
      "unit": "widgets",
      "capacity": 100,
      "utilization": 65.2,
      "rate": 0.041,
      "cost": "$2,736.74",
      "currency": "USD"
    },
    {
      "period": "month",
      "year": 2022,
      "month": 1,
      "beginDate": "1/1/2022",
      "endDate": "1/31/2022",
      "service": "uncategorized",
      "unit": "widgets",
      "capacity": 100,
      "utilization": 66.3,
      "rate": 0.041,
      "cost": "$2,784.27",
      "currency": "USD"
    },
    {
      "period": "month",
      "year": 2020,
      "month": 2,
      "beginDate": "2/1/2020",
      "endDate": "2/29/2020",
      "service": "other",
      "unit": "widgets",
      "capacity": 100,
      "utilization": 17,
      "rate": 0.041,
      "cost": "$713.73",
      "currency": "USD"
    },
    {
      "period": "month",
      "year": 2020,
      "month": 3,
      "beginDate": "3/1/2020",
      "endDate": "3/31/2020",
      "service": "other",
      "unit": "widgets",
      "capacity": 100,
      "utilization": 16.2,
      "rate": 0.041,
      "cost": "$679.27",
      "currency": "USD"
    },
    {
      "period": "month",
      "year": 2020,
      "month": 4,
      "beginDate": "4/1/2020",
      "endDate": "4/30/2020",
      "service": "other",
      "unit": "widgets",
      "capacity": 100,
      "utilization": 15.4,
      "rate": 0.041,
      "cost": "$648.06",
      "currency": "USD"
    },
    {
      "period": "month",
      "year": 2020,
      "month": 5,
      "beginDate": "5/1/2020",
      "endDate": "5/31/2020",
      "service": "other",
      "unit": "widgets",
      "capacity": 100,
      "utilization": 14.8,
      "rate": 0.041,
      "cost": "$621.92",
      "currency": "USD"
    },
    {
      "period": "month",
      "year": 2020,
      "month": 6,
      "beginDate": "6/1/2020",
      "endDate": "6/30/2020",
      "service": "other",
      "unit": "widgets",
      "capacity": 100,
      "utilization": 14.4,
      "rate": 0.041,
      "cost": "$604.71",
      "currency": "USD"
    },
    {
      "period": "month",
      "year": 2020,
      "month": 7,
      "beginDate": "7/1/2020",
      "endDate": "7/31/2020",
      "service": "other",
      "unit": "widgets",
      "capacity": 100,
      "utilization": 14.2,
      "rate": 0.041,
      "cost": "$597.06",
      "currency": "USD"
    },
    {
      "period": "month",
      "year": 2020,
      "month": 8,
      "beginDate": "8/1/2020",
      "endDate": "8/31/2020",
      "service": "other",
      "unit": "widgets",
      "capacity": 100,
      "utilization": 13.6,
      "rate": 0.041,
      "cost": "$570.26",
      "currency": "USD"
    },
    {
      "period": "month",
      "year": 2020,
      "month": 9,
      "beginDate": "9/1/2020",
      "endDate": "9/30/2020",
      "service": "other",
      "unit": "widgets",
      "capacity": 100,
      "utilization": 13.2,
      "rate": 0.041,
      "cost": "$554.87",
      "currency": "USD"
    },
    {
      "period": "month",
      "year": 2020,
      "month": 10,
      "beginDate": "10/1/2020",
      "endDate": "10/31/2020",
      "service": "other",
      "unit": "widgets",
      "capacity": 100,
      "utilization": 13.4,
      "rate": 0.041,
      "cost": "$560.82",
      "currency": "USD"
    },
    {
      "period": "month",
      "year": 2020,
      "month": 11,
      "beginDate": "11/1/2020",
      "endDate": "11/30/2020",
      "service": "other",
      "unit": "widgets",
      "capacity": 100,
      "utilization": 12.9,
      "rate": 0.041,
      "cost": "$540.08",
      "currency": "USD"
    },
    {
      "period": "month",
      "year": 2020,
      "month": 12,
      "beginDate": "12/1/2020",
      "endDate": "12/31/2020",
      "service": "other",
      "unit": "widgets",
      "capacity": 100,
      "utilization": 13.2,
      "rate": 0.041,
      "cost": "$555.63",
      "currency": "USD"
    },
    {
      "period": "month",
      "year": 2021,
      "month": 1,
      "beginDate": "1/1/2021",
      "endDate": "1/31/2021",
      "service": "other",
      "unit": "widgets",
      "capacity": 100,
      "utilization": 13.7,
      "rate": 0.041,
      "cost": "$576.46",
      "currency": "USD"
    },
    {
      "period": "month",
      "year": 2021,
      "month": 2,
      "beginDate": "2/1/2021",
      "endDate": "2/28/2021",
      "service": "other",
      "unit": "widgets",
      "capacity": 100,
      "utilization": 14.1,
      "rate": 0.041,
      "cost": "$591.70",
      "currency": "USD"
    },
    {
      "period": "month",
      "year": 2021,
      "month": 3,
      "beginDate": "3/1/2021",
      "endDate": "3/31/2021",
      "service": "other",
      "unit": "widgets",
      "capacity": 100,
      "utilization": 14,
      "rate": 0.041,
      "cost": "$588.08",
      "currency": "USD"
    },
    {
      "period": "month",
      "year": 2021,
      "month": 4,
      "beginDate": "4/1/2021",
      "endDate": "4/30/2021",
      "service": "other",
      "unit": "widgets",
      "capacity": 100,
      "utilization": 14.6,
      "rate": 0.041,
      "cost": "$611.43",
      "currency": "USD"
    },
    {
      "period": "month",
      "year": 2021,
      "month": 5,
      "beginDate": "5/1/2021",
      "endDate": "5/31/2021",
      "service": "other",
      "unit": "widgets",
      "capacity": 100,
      "utilization": 13.8,
      "rate": 0.041,
      "cost": "$580.92",
      "currency": "USD"
    },
    {
      "period": "month",
      "year": 2021,
      "month": 6,
      "beginDate": "6/1/2021",
      "endDate": "6/30/2021",
      "service": "other",
      "unit": "widgets",
      "capacity": 100,
      "utilization": 13.9,
      "rate": 0.041,
      "cost": "$585.05",
      "currency": "USD"
    },
    {
      "period": "month",
      "year": 2021,
      "month": 7,
      "beginDate": "7/1/2021",
      "endDate": "7/31/2021",
      "service": "other",
      "unit": "widgets",
      "capacity": 100,
      "utilization": 14.5,
      "rate": 0.041,
      "cost": "$610.53",
      "currency": "USD"
    },
    {
      "period": "month",
      "year": 2021,
      "month": 8,
      "beginDate": "8/1/2021",
      "endDate": "8/31/2021",
      "service": "other",
      "unit": "widgets",
      "capacity": 100,
      "utilization": 14,
      "rate": 0.041,
      "cost": "$586.74",
      "currency": "USD"
    },
    {
      "period": "month",
      "year": 2021,
      "month": 9,
      "beginDate": "9/1/2021",
      "endDate": "9/30/2021",
      "service": "other",
      "unit": "widgets",
      "capacity": 100,
      "utilization": 14.3,
      "rate": 0.041,
      "cost": "$601.94",
      "currency": "USD"
    },
    {
      "period": "month",
      "year": 2021,
      "month": 10,
      "beginDate": "10/1/2021",
      "endDate": "10/31/2021",
      "service": "other",
      "unit": "widgets",
      "capacity": 100,
      "utilization": 14.6,
      "rate": 0.041,
      "cost": "$613.93",
      "currency": "USD"
    },
    {
      "period": "month",
      "year": 2021,
      "month": 11,
      "beginDate": "11/1/2021",
      "endDate": "11/30/2021",
      "service": "other",
      "unit": "widgets",
      "capacity": 100,
      "utilization": 15.1,
      "rate": 0.041,
      "cost": "$635.45",
      "currency": "USD"
    },
    {
      "period": "month",
      "year": 2021,
      "month": 12,
      "beginDate": "12/1/2021",
      "endDate": "12/31/2021",
      "service": "other",
      "unit": "widgets",
      "capacity": 100,
      "utilization": 15.4,
      "rate": 0.041,
      "cost": "$648.14",
      "currency": "USD"
    },
    {
      "period": "month",
      "year": 2022,
      "month": 1,
      "beginDate": "1/1/2022",
      "endDate": "1/31/2022",
      "service": "other",
      "unit": "widgets",
      "capacity": 100,
      "utilization": 15,
      "rate": 0.041,
      "cost": "$628.34",
      "currency": "USD"
    }
  ]
}
